{
  "_verify_import": {
    "created_at": 1781399542.5433736,
    "last_used": 1781796270.5518498,
    "use_count": 111,
    "reinforcement_count": 0,
    "base_confidence": 0.5
  },
  "Customer Refund Processing": {
    "created_at": 1781399542.5590432,
    "last_used": 1781796270.670592,
    "use_count": 111,
    "reinforcement_count": 0,
    "base_confidence": 0.5
  },
  "Data Property Rights Registration": {
    "created_at": 1781399542.5731492,
    "last_used": 1781796270.696016,
    "use_count": 111,
    "reinforcement_count": 0,
    "base_confidence": 0.5
  },
  "digested-doc": {
    "created_at": 1781399542.5876503,
    "last_used": 1781796270.747631,
    "use_count": 111,
    "reinforcement_count": 0,
    "base_confidence": 0.5
  },
  "Export Data from App": {
    "created_at": 1781399542.601724,
    "last_used": 1781796270.8356812,
    "use_count": 111,
    "reinforcement_count": 0,
    "base_confidence": 0.5
  },
  "Export Settings": {
    "created_at": 1781399542.6147933,
    "last_used": 1781796270.863453,
    "use_count": 111,
    "reinforcement_count": 0,
    "base_confidence": 0.5
  },
  "mcp-extracted": {
    "created_at": 1781399542.6321802,
    "last_used": 1781796271.0417657,
    "use_count": 111,
    "reinforcement_count": 0,
    "base_confidence": 0.5
  },
  "REST API Design Fundamentals": {
    "created_at": 1781399542.6446226,
    "last_used": 1781796271.1235034,
    "use_count": 111,
    "reinforcement_count": 0,
    "base_confidence": 0.5
  },
  "rt-test": {
    "created_at": 1781399542.6607096,
    "last_used": 1781796271.2094498,
    "use_count": 111,
    "reinforcement_count": 0,
    "base_confidence": 0.5
  },
  "test-agent-factory": {
    "created_at": 1781399542.6741805,
    "last_used": 1781796271.2897081,
    "use_count": 111,
    "reinforcement_count": 0,
    "base_confidence": 0.5
  },
  "test-bridge": {
    "created_at": 1781399542.6977654,
    "last_used": 1781796271.3176267,
    "use_count": 111,
    "reinforcement_count": 0,
    "base_confidence": 0.5
  },
  "test-hermes-bridge": {
    "created_at": 1781399542.7108119,
    "last_used": 1781796271.3449488,
    "use_count": 111,
    "reinforcement_count": 0,
    "base_confidence": 0.5
  },
  "微信文章深度消化指南": {
    "created_at": 1781399542.7232547,
    "last_used": 1781796272.1946166,
    "use_count": 111,
    "reinforcement_count": 0,
    "base_confidence": 0.5
  },
  "数据产权登记与-三权分置-解读": {
    "created_at": 1781399542.735638,
    "last_used": 1781796272.374157,
    "use_count": 111,
    "reinforcement_count": 0,
    "base_confidence": 0.5
  },
  "数据产权登记凭证的效力与边界": {
    "created_at": 1781399542.7480104,
    "last_used": 1781796272.409816,
    "use_count": 111,
    "reinforcement_count": 0,
    "base_confidence": 0.5
  },
  "数据产权登记制度与三权分置解读": {
    "created_at": 1781399542.7603128,
    "last_used": 1781796272.4446564,
    "use_count": 111,
    "reinforcement_count": 0,
    "base_confidence": 0.5
  },
  "数据产权登记实操指南": {
    "created_at": 1781399542.77261,
    "last_used": 1781796272.4727564,
    "use_count": 111,
    "reinforcement_count": 0,
    "base_confidence": 0.5
  },
  "integration-test-save-load": {
    "created_at": 1781401542.7316105,
    "last_used": 1781796270.9845712,
    "use_count": 103,
    "reinforcement_count": 0,
    "base_confidence": 0.5
  },
  "integration-test-versions": {
    "created_at": 1781401542.7441666,
    "last_used": 1781796271.0127642,
    "use_count": 103,
    "reinforcement_count": 0,
    "base_confidence": 0.5
  },
  "订单提交测试提取流程": {
    "created_at": 1781401542.8975234,
    "last_used": 1781796273.1433399,
    "use_count": 103,
    "reinforcement_count": 0,
    "base_confidence": 0.5
  },
  "test extraction": {
    "created_at": 1781401656.1917546,
    "last_used": 1781796271.235264,
    "use_count": 98,
    "reinforcement_count": 0,
    "base_confidence": 0.5
  },
  "测试提取流程": {
    "created_at": 1781402197.5824177,
    "last_used": 1781796272.6433694,
    "use_count": 95,
    "reinforcement_count": 0,
    "base_confidence": 0.5
  },
  "订单提交后的字段提取与校验流程": {
    "created_at": 1781402682.1763592,
    "last_used": 1781796273.0144076,
    "use_count": 89,
    "reinforcement_count": 0,
    "base_confidence": 0.5
  },
  "订单测试提取流程": {
    "created_at": 1781405567.8178918,
    "last_used": 1781796273.322706,
    "use_count": 85,
    "reinforcement_count": 0,
    "base_confidence": 0.5
  },
  "订单备注信息提取流程": {
    "created_at": 1781405971.0547838,
    "last_used": 1781796272.9872382,
    "use_count": 80,
    "reinforcement_count": 0,
    "base_confidence": 0.5
  },
  "订单退款处理流程": {
    "created_at": 1781405971.122543,
    "last_used": 1781796273.424271,
    "use_count": 80,
    "reinforcement_count": 0,
    "base_confidence": 0.5
  },
  "订单提交时数据提取与校验流程": {
    "created_at": 1781406398.4896421,
    "last_used": 1781796273.0690997,
    "use_count": 67,
    "reinforcement_count": 0,
    "base_confidence": 0.5
  },
  "订单测试信息提取流程": {
    "created_at": 1781406542.9552505,
    "last_used": 1781796273.2494977,
    "use_count": 63,
    "reinforcement_count": 0,
    "base_confidence": 0.5
  },
  "测试抽取流程- 草稿 v0.1": {
    "created_at": 1781406876.3970988,
    "last_used": 1781796272.532285,
    "use_count": 59,
    "reinforcement_count": 0,
    "base_confidence": 0.5
  },
  "测试抽取流程- 草稿 v0.2": {
    "created_at": 1781406876.399622,
    "last_used": 1781796272.560224,
    "use_count": 59,
    "reinforcement_count": 0,
    "base_confidence": 0.5
  },
  "测试抽取流程- 草稿 v0.3": {
    "created_at": 1781406876.4193442,
    "last_used": 1781796272.586443,
    "use_count": 59,
    "reinforcement_count": 0,
    "base_confidence": 0.5
  },
  "测试抽取流程- 草稿 v0.4": {
    "created_at": 1781406876.4394917,
    "last_used": 1781796272.6182468,
    "use_count": 59,
    "reinforcement_count": 0,
    "base_confidence": 0.5
  },
  "订单数据提取测试流程": {
    "created_at": 1781407354.5692906,
    "last_used": 1781796273.225043,
    "use_count": 55,
    "reinforcement_count": 0,
    "base_confidence": 0.5
  },
  "dispatch-confirm-test": {
    "created_at": 1781407578.8258572,
    "last_used": 1781796270.7759607,
    "use_count": 53,
    "reinforcement_count": 0,
    "base_confidence": 0.5
  },
  "测试数据提取流程": {
    "created_at": 1781407706.292265,
    "last_used": 1781796272.6974757,
    "use_count": 51,
    "reinforcement_count": 0,
    "base_confidence": 0.5
  },
  "测试提取流程设计": {
    "created_at": 1781408031.9309533,
    "last_used": 1781796272.67105,
    "use_count": 47,
    "reinforcement_count": 0,
    "base_confidence": 0.5
  },
  "订单触发式测试提取流水线": {
    "created_at": 1781408434.9452403,
    "last_used": 1781796273.3709137,
    "use_count": 43,
    "reinforcement_count": 0,
    "base_confidence": 0.5
  },
  "GitHub PR 代码审查流程": {
    "created_at": 1781411496.65376,
    "last_used": 1781796270.9227421,
    "use_count": 37,
    "reinforcement_count": 0,
    "base_confidence": 0.5
  },
  "PR审查流程": {
    "created_at": 1781411496.7116976,
    "last_used": 1781796271.0977883,
    "use_count": 37,
    "reinforcement_count": 0,
    "base_confidence": 0.5
  },
  "套飞书报销审批的处理流程": {
    "created_at": 1781411496.834912,
    "last_used": 1781796271.7606738,
    "use_count": 37,
    "reinforcement_count": 0,
    "base_confidence": 0.5
  },
  "淘宝小店数码配件退款处理流程": {
    "created_at": 1781411497.060623,
    "last_used": 1781796272.7482235,
    "use_count": 37,
    "reinforcement_count": 0,
    "base_confidence": 0.5
  },
  "淘宝退款处理": {
    "created_at": 1781411497.0641263,
    "last_used": 1781796272.7771318,
    "use_count": 37,
    "reinforcement_count": 0,
    "base_confidence": 0.5
  },
  "电商客服退款处理标准流程": {
    "created_at": 1781411497.0818858,
    "last_used": 1781796272.8397536,
    "use_count": 37,
    "reinforcement_count": 0,
    "base_confidence": 0.5
  },
  "电商客服退款处理流程": {
    "created_at": 1781411497.1021535,
    "last_used": 1781796272.8718634,
    "use_count": 37,
    "reinforcement_count": 0,
    "base_confidence": 0.5
  },
  "电商客服退款标准流程": {
    "created_at": 1781411497.1199052,
    "last_used": 1781796272.9013429,
    "use_count": 37,
    "reinforcement_count": 0,
    "base_confidence": 0.5
  },
  "订单信息测试提取流程": {
    "created_at": 1781411497.137392,
    "last_used": 1781796272.961342,
    "use_count": 37,
    "reinforcement_count": 0,
    "base_confidence": 0.5
  },
  "订单测试字段提取流程": {
    "created_at": 1781411497.268275,
    "last_used": 1781796273.275407,
    "use_count": 37,
    "reinforcement_count": 0,
    "base_confidence": 0.5
  },
  "费用报销审批": {
    "created_at": 1781411497.3418496,
    "last_used": 1781796273.486283,
    "use_count": 37,
    "reinforcement_count": 0,
    "base_confidence": 0.5
  },
  "退款处理": {
    "created_at": 1781411497.3456712,
    "last_used": 1781796273.5792878,
    "use_count": 37,
    "reinforcement_count": 0,
    "base_confidence": 0.5
  },
  "飞书报销审批处理流程": {
    "created_at": 1781411497.3666852,
    "last_used": 1781796273.776896,
    "use_count": 37,
    "reinforcement_count": 0,
    "base_confidence": 0.5
  },
  "订单测试提取流": {
    "created_at": 1781411813.6486247,
    "last_used": 1781796273.2994294,
    "use_count": 35,
    "reinforcement_count": 0,
    "base_confidence": 0.5
  },
  "订单提交提取流程测试技能": {
    "created_at": 1781411991.6754012,
    "last_used": 1781796273.0390444,
    "use_count": 31,
    "reinforcement_count": 0,
    "base_confidence": 0.5
  },
  "test extraction flow": {
    "created_at": 1781412077.9612997,
    "last_used": 1781796271.2626624,
    "use_count": 29,
    "reinforcement_count": 0,
    "base_confidence": 0.5
  },
  "__legacy_other__": {
    "created_at": 1781424188.4492795,
    "last_used": 1781796270.523937,
    "use_count": 27,
    "reinforcement_count": 0,
    "base_confidence": 0.5
  },
  "ep-ui-test": {
    "created_at": 1781424188.5332522,
    "last_used": 1781796270.8074617,
    "use_count": 27,
    "reinforcement_count": 0,
    "base_confidence": 0.5
  },
  "cli-test-skill": {
    "created_at": 1781516201.6600397,
    "last_used": 1781796270.578986,
    "use_count": 26,
    "reinforcement_count": 0,
    "base_confidence": 0.5
  },
  "cold-start-interview": {
    "created_at": 1781516201.6776996,
    "last_used": 1781796270.6070664,
    "use_count": 26,
    "reinforcement_count": 0,
    "base_confidence": 0.5
  },
  "deep-digest": {
    "created_at": 1781516201.7188666,
    "last_used": 1781796270.719864,
    "use_count": 26,
    "reinforcement_count": 0,
    "base_confidence": 0.5
  },
  "phase-a-export-test": {
    "created_at": 1781516201.8508184,
    "last_used": 1781796271.0691452,
    "use_count": 26,
    "reinforcement_count": 0,
    "base_confidence": 0.5
  },
  "严重故障协同处理": {
    "created_at": 1781516202.002144,
    "last_used": 1781796271.3717906,
    "use_count": 26,
    "reinforcement_count": 0,
    "base_confidence": 0.5
  },
  "严重故障处理": {
    "created_at": 1781516202.0230417,
    "last_used": 1781796271.3972368,
    "use_count": 26,
    "reinforcement_count": 0,
    "base_confidence": 0.5
  },
  "合同审核": {
    "created_at": 1781516202.0423455,
    "last_used": 1781796271.5889726,
    "use_count": 26,
    "reinforcement_count": 0,
    "base_confidence": 0.5
  },
  "合同审核 - 条款比对与风险识别": {
    "created_at": 1781516202.05955,
    "last_used": 1781796271.6167648,
    "use_count": 26,
    "reinforcement_count": 0,
    "base_confidence": 0.5
  },
  "合同审核助手": {
    "created_at": 1781516202.0759332,
    "last_used": 1781796271.6483843,
    "use_count": 26,
    "reinforcement_count": 0,
    "base_confidence": 0.5
  },
  "处理退款": {
    "created_at": 1781516202.091543,
    "last_used": 1781796271.7344556,
    "use_count": 26,
    "reinforcement_count": 0,
    "base_confidence": 0.5
  },
  "客户退款处理": {
    "created_at": 1781516202.1261234,
    "last_used": 1781796271.9450045,
    "use_count": 26,
    "reinforcement_count": 0,
    "base_confidence": 0.5
  },
  "客服工单处理": {
    "created_at": 1781516202.14188,
    "last_used": 1781796271.9706755,
    "use_count": 26,
    "reinforcement_count": 0,
    "base_confidence": 0.5
  },
  "工单分流处理": {
    "created_at": 1781516202.1581783,
    "last_used": 1781796271.9975283,
    "use_count": 26,
    "reinforcement_count": 0,
    "base_confidence": 0.5
  },
  "工单分类处理": {
    "created_at": 1781516202.1747437,
    "last_used": 1781796272.0284896,
    "use_count": 26,
    "reinforcement_count": 0,
    "base_confidence": 0.5
  },
  "工单分诊与SLA管理": {
    "created_at": 1781516202.1771822,
    "last_used": 1781796272.0577006,
    "use_count": 26,
    "reinforcement_count": 0,
    "base_confidence": 0.5
  },
  "工单处理": {
    "created_at": 1781516202.1980262,
    "last_used": 1781796272.0846815,
    "use_count": 26,
    "reinforcement_count": 0,
    "base_confidence": 0.5
  },
  "工单处理与升级": {
    "created_at": 1781516202.2155802,
    "last_used": 1781796272.1130564,
    "use_count": 26,
    "reinforcement_count": 0,
    "base_confidence": 0.5
  },
  "工单处理流程": {
    "created_at": 1781516202.23428,
    "last_used": 1781796272.1410189,
    "use_count": 26,
    "reinforcement_count": 0,
    "base_confidence": 0.5
  },
  "工单处理规范": {
    "created_at": 1781516202.2506704,
    "last_used": 1781796272.1711552,
    "use_count": 26,
    "reinforcement_count": 0,
    "base_confidence": 0.5
  },
  "技术支持工单处理": {
    "created_at": 1781516202.2846024,
    "last_used": 1781796272.2864554,
    "use_count": 26,
    "reinforcement_count": 0,
    "base_confidence": 0.5
  },
  "技术支持工单处理流程": {
    "created_at": 1781516202.3011174,
    "last_used": 1781796272.3146293,
    "use_count": 26,
    "reinforcement_count": 0,
    "base_confidence": 0.5
  },
  "测试数据提取流程设计": {
    "created_at": 1781516202.505279,
    "last_used": 1781796272.7223885,
    "use_count": 26,
    "reinforcement_count": 0,
    "base_confidence": 0.5
  },
  "订单提交测试提取流": {
    "created_at": 1781516202.6860485,
    "last_used": 1781796273.1,
    "use_count": 26,
    "reinforcement_count": 0,
    "base_confidence": 0.5
  },
  "订单触发测试提取流程": {
    "created_at": 1781516202.777535,
    "last_used": 1781796273.398544,
    "use_count": 26,
    "reinforcement_count": 0,
    "base_confidence": 0.5
  },
  "销售合同审核": {
    "created_at": 1781516202.8583493,
    "last_used": 1781796273.6503725,
    "use_count": 26,
    "reinforcement_count": 0,
    "base_confidence": 0.5
  },
  "销售合同审核助手": {
    "created_at": 1781516202.8770273,
    "last_used": 1781796273.6772635,
    "use_count": 26,
    "reinforcement_count": 0,
    "base_confidence": 0.5
  },
  "订单触发型测试提取流程": {
    "created_at": 1781516496.6887834,
    "last_used": 1781796273.3470178,
    "use_count": 24,
    "reinforcement_count": 0,
    "base_confidence": 0.5
  },
  "订单提交触发-数据提取与测试流": {
    "created_at": 1781516643.8596463,
    "last_used": 1781796273.1719959,
    "use_count": 22,
    "reinforcement_count": 0,
    "base_confidence": 0.5
  },
  "订单提交触发-数据提取流": {
    "created_at": 1781516643.8800788,
    "last_used": 1781796273.199952,
    "use_count": 22,
    "reinforcement_count": 0,
    "base_confidence": 0.5
  },
  "REST API 设计流程": {
    "created_at": 1781530140.4707508,
    "last_used": 1781796271.1532736,
    "use_count": 20,
    "reinforcement_count": 0,
    "base_confidence": 0.5
  },
  "REST API 设计流程专家": {
    "created_at": 1781530140.4905827,
    "last_used": 1781796271.1837153,
    "use_count": 20,
    "reinforcement_count": 0,
    "base_confidence": 0.5
  },
  "客户入职流程自动化": {
    "created_at": 1781530140.768283,
    "last_used": 1781796271.9131973,
    "use_count": 20,
    "reinforcement_count": 0,
    "base_confidence": 0.5
  },
  "数据分析周报流程。收集各部门数据": {
    "created_at": 1781530141.1035216,
    "last_used": 1781796272.5035508,
    "use_count": 20,
    "reinforcement_count": 0,
    "base_confidence": 0.5
  },
  "代码审查": {
    "created_at": 1781532606.2673116,
    "last_used": 1781796271.4644873,
    "use_count": 18,
    "reinforcement_count": 0,
    "base_confidence": 0.5
  },
  "客户入职流程": {
    "created_at": 1781532606.4035208,
    "last_used": 1781796271.849518,
    "use_count": 18,
    "reinforcement_count": 0,
    "base_confidence": 0.5
  },
  "客户入职流程 -": {
    "created_at": 1781532606.429705,
    "last_used": 1781796271.8826237,
    "use_count": 18,
    "reinforcement_count": 0,
    "base_confidence": 0.5
  },
  "技术面试": {
    "created_at": 1781532606.7427394,
    "last_used": 1781796272.3480544,
    "use_count": 18,
    "reinforcement_count": 0,
    "base_confidence": 0.5
  },
  "需求发布上线": {
    "created_at": 1781532607.619365,
    "last_used": 1781796273.7363029,
    "use_count": 18,
    "reinforcement_count": 0,
    "base_confidence": 0.5
  },
  "GitHub PR": {
    "created_at": 1781594676.5314198,
    "last_used": 1781796270.8935795,
    "use_count": 9,
    "reinforcement_count": 0,
    "base_confidence": 0.5
  },
  "低于需改进线的员工进入P": {
    "created_at": 1781594676.9822025,
    "last_used": 1781796271.4946437,
    "use_count": 9,
    "reinforcement_count": 0,
    "base_confidence": 0.5
  },
  "供应商评估": {
    "created_at": 1781594677.0066843,
    "last_used": 1781796271.5596542,
    "use_count": 9,
    "reinforcement_count": 0,
    "base_confidence": 0.5
  },
  "培训课程设计": {
    "created_at": 1781594677.1008399,
    "last_used": 1781796271.7068,
    "use_count": 9,
    "reinforcement_count": 0,
    "base_confidence": 0.5
  },
  "安全审计": {
    "created_at": 1781594677.170154,
    "last_used": 1781796271.8216155,
    "use_count": 9,
    "reinforcement_count": 0,
    "base_confidence": 0.5
  },
  "电商客服退款处理": {
    "created_at": 1781594677.844185,
    "last_used": 1781796272.8109334,
    "use_count": 9,
    "reinforcement_count": 0,
    "base_confidence": 0.5
  },
  "运维事故响应技能": {
    "created_at": 1781594678.3561409,
    "last_used": 1781796273.5157933,
    "use_count": 9,
    "reinforcement_count": 0,
    "base_confidence": 0.5
  },
  "运营级CSV清洗工坊": {
    "created_at": 1781594678.3801484,
    "last_used": 1781796273.543775,
    "use_count": 9,
    "reinforcement_count": 0,
    "base_confidence": 0.5
  },
  "采购审批": {
    "created_at": 1781594678.4238229,
    "last_used": 1781796273.6082158,
    "use_count": 9,
    "reinforcement_count": 0,
    "base_confidence": 0.5
  },
  "产品需求评审": {
    "created_at": 1781623017.0755978,
    "last_used": 1781796271.4334161,
    "use_count": 7,
    "reinforcement_count": 0,
    "base_confidence": 0.5
  },
  "供应商准入": {
    "created_at": 1781623017.1513107,
    "last_used": 1781796271.524383,
    "use_count": 7,
    "reinforcement_count": 0,
    "base_confidence": 0.5
  },
  "营销内容合规审查流水线": {
    "created_at": 1781623018.2189233,
    "last_used": 1781796272.9342628,
    "use_count": 7,
    "reinforcement_count": 0,
    "base_confidence": 0.5
  },
  "CSV数据清洗助手": {
    "created_at": 1781644619.4326053,
    "last_used": 1781796270.6380324,
    "use_count": 6,
    "reinforcement_count": 0,
    "base_confidence": 0.5
  },
  "GitHub Pull": {
    "created_at": 1781644619.650683,
    "last_used": 1781796270.953252,
    "use_count": 6,
    "reinforcement_count": 0,
    "base_confidence": 0.5
  },
  "合同法务审核助手": {
    "created_at": 1781748839.171673,
    "last_used": 1781796271.679602,
    "use_count": 5,
    "reinforcement_count": 0,
    "base_confidence": 0.5
  },
  "安全合规审计助手": {
    "created_at": 1781748839.2823236,
    "last_used": 1781796271.792318,
    "use_count": 5,
    "reinforcement_count": 0,
    "base_confidence": 0.5
  },
  "我想做一个电商客服退款处": {
    "created_at": 1781748839.6608937,
    "last_used": 1781796272.226608,
    "use_count": 5,
    "reinforcement_count": 0,
    "base_confidence": 0.5
  },
  "我要一个 CSV": {
    "created_at": 1781748839.6885993,
    "last_used": 1781796272.2567463,
    "use_count": 5,
    "reinforcement_count": 0,
    "base_confidence": 0.5
  },
  "财务报销审计助手": {
    "created_at": 1781748840.742803,
    "last_used": 1781796273.4599411,
    "use_count": 5,
    "reinforcement_count": 0,
    "base_confidence": 0.5
  },
  "门诊分诊": {
    "created_at": 1781796112.3431582,
    "last_used": 1781796273.707963,
    "use_count": 4,
    "reinforcement_count": 0,
    "base_confidence": 0.5
  }
}