{
  "session_id": "src_21d8731ad2f2",
  "source_url": "session:generalize_1781744395-security",
  "source_title": "安全合规审计助手",
  "created_at": 1781744888.3184657,
  "summary": {
    "total_items": 1,
    "by_category": {
      "heuristic": 1
    },
    "by_epistemic_level": {
      "knowledge": 1
    },
    "confidence_distribution": {
      "high": 1,
      "medium": 0,
      "low": 0
    }
  },
  "items": [
    {
      "item_id": "ki_32d356ed",
      "content": "技能「安全合规审计助手」: 这个流程解决如何系统化执行等保/内部基线安全审计，从范围确定到整改闭环的全过程管理。",
      "category": "heuristic",
      "confidence": 1.0,
      "epistemic_level": "knowledge",
      "is_valid": true,
      "strength": 1.65,
      "source": {
        "url": "session:generalize_1781744395-security",
        "paragraph": 0
      },
      "pipeline_steps": 0,
      "graph_node": "",
      "related_items": [],
      "related_count": 0,
      "affected_skills": [
        {
          "skill_name": "安全合规审计助手",
          "score_delta": 1.0,
          "timestamp": 1781744888.3181732
        }
      ],
      "access_count": 7,
      "created_at": 1781744888.3181732,
      "valid_at": 0.0,
      "invalid_at": 0.0,
      "superseded_by": "",
      "last_accessed": 1781744888.3181732
    }
  ]
}